Workbook

Sheet How to use
A1: ECFD Egyptian Call Lexicon
A2: The words Egyptians actually use on the phone: Arabized English verbs (اتشيك، كنسل)، slang, request verbs, secret objects, scam phrases.
A4: What it is used for
A5: 1. NLP detection: one entry per stem; the matcher strips Arabic prefixes/suffixes (ه، ب، ات … ها، لي، هولي) so كنسل also catches هكنسلهالك.
A6: 2. ASR testing: every Example sentence is a line to record (Test 1 / bake-off).
A7: 3. ASR fine-tuning: the example sentences + recordings become training data.
A9: How to add or check words (yellow cells are for you)
A10: • Add a new row at the bottom of the Lexicon tab. Fill Word, Other spellings, Meaning, Category, Risk role, Said by, Example sentence, Added by.
A11: • Every row starts as 'Claude draft'. A native speaker changes Status to 'Verified' (or 'Rejected' / 'Needs discussion').
A12: • Other spellings: every way the ASR might write it - Arabic script, Latin, with/without ال. Separate with |
A13: • Example sentence: how a real person would say it on a call - not formal Arabic.
A14: • Rows marked 'verify' in Notes (mostly money slang) are ones Claude is unsure about.
... A24: Legend: yellow cells = to fill in / verify

Sheet Lexicon
A1: ID | B1: Word (as spoken) | C1: Other spellings (| separated) | D1: Meaning (English) | E1: Category | F1: Concept | G1: Risk role | H1: Said by | I1: Example sentence (Egyptian) | J1: Status | K1: Added by | L1: Notes
A2: L001 | B2: اتشيك | C2: شيّك|هشيّك|بشيّك|اتشيكلك|مشيّك | D2: check | E2: Arabized English verb | F2: CHECK | G2: NEUTRAL | H2: Both | I2: ثواني اتشيك لحضرتك | J2: Claude draft | K2: Claude | L2: شيك can also mean a bank cheque (شيك بنكي) - context decides
A3: L002 | B3: كنسل | C3: هكنسل|كنسلها|اتكنسل|ماتكنسلش|هكنسلهالك | D3: cancel | E3: Arabized English verb | F3: CANCEL | G3: SCORE | H3: Both | I3: هكنسلهالك من عندي بس محتاج الكود | J3: Claude draft | K3: Claude
A4: L003 | B4: فورود | C4: فورودهولي|فوروردلي|اعمل فورورد|فوروردها | D4: forward | E4: Arabized English verb | F4: FORWARD | G4: HARD | H4: Caller | I4: فورودهولي الرسالة اللي جاتلك | J4: Claude draft | K4: Claude | L4: forwarding an SMS = sharing the OTP
A5: L004 | B5: سيّف | C5: سيفها|اعمل سيف|متسيّفة | D5: save | E5: Arabized English verb | F5: SAVE | G5: NEUTRAL | H5: Both | I5: سيّف الرقم ده عندك | J5: Claude draft | K5: Claude
A6: L005 | B6: شيّر | C6: اعمل شير|شيرلي|شيّر الشاشة|شير سكرين | D6: share | E6: Arabized English verb | F6: SHARE | G6: HARD | H6: Caller | I6: اعمل شير سكرين عشان أشوف المشكلة | J6: Claude draft | K6: Claude | L6: screen share = remote access
A7: L006 | B7: داونلود | C7: نزّل|اعمل داونلود|داونلودها | D7: download | E7: Arabized English verb | F7: INSTALL | G7: HARD | H7: Caller | I7: اعمل داونلود للأبلكيشن ده | J7: Claude draft | K7: Claude
A8: L007 | B8: ابلود | C8: اعمل ابلود|ابلودها | D8: upload | E8: Arabized English verb | F8: UPLOAD | G8: SCORE | H8: Caller | I8: ابلود صورة البطاقة هنا | J8: Claude draft | K8: Claude | L8: ID photo upload
A9: L008 | B9: انستول | C9: اعمل انستول|انستولها|سطّب|سطّبها | D9: install | E9: Arabized English verb | F9: INSTALL | G9: HARD | H9: Caller | I9: سطّب البرنامج ده وانا هكمل معاك | J9: Claude draft | K9: Claude
A10: L009 | B10: اكسبت | C10: اعمل اكسبت|اكسبتها|دوس اكسبت | D10: accept | E10: Arabized English verb | F10: APPROVE | G10: HARD | H10: Caller | I10: هيجيلك طلب دوس اكسبت | J10: Claude draft | K10: Claude
A11: L010 | B11: كونفيرم | C11: اعمل كونفيرم|كونفرم|كونفيرمها | D11: confirm | E11: Arabized English verb | F11: APPROVE | G11: HARD | H11: Caller | I11: دوس كونفيرم عشان العملية تخلص | J11: Claude draft | K11: Claude
A12: L011 | B12: أبروف | C12: ابروف|اعمل ابروف|ابروفها | D12: approve | E12: Arabized English verb | F12: APPROVE | G12: HARD | H12: Caller | I12: اعمل أبروف للعملية اللي هتظهرلك | J12: Claude draft | K12: Claude
A13: L012 | B13: ابديت | C13: اعمل ابديت|أبديت|ابديتها|اتأبدت | D13: update | E13: Arabized English verb | F13: UPDATE_DATA | G13: SCORE | H13: Caller | I13: لازم نعمل ابديت لبياناتك النهارده | J13: Claude draft | K13: Claude
A14: L013 | B14: ريست | C14: ريسيت|اعمل ريست|ريستها | D14: reset | E14: Arabized English verb | F14: RESET | G14: SCORE | H14: Both | I14: هعملك ريست للباسورد | J14: Claude draft | K14: Claude
A15: L014 | B15: ريستارت | C15: اعمل ريستارت|ريستارتها | D15: restart | E15: Arabized English verb | F15: RESTART | G15: NEUTRAL | H15: Both | I15: اعمل ريستارت للموبايل | J15: Claude draft | K15: Claude
A16: L015 | B16: فورمات | C16: اعمل فورمات|فرمت|اتفرمت | D16: format (wipe) | E16: Arabized English verb | F16: FORMAT | G16: NEUTRAL | H16: Both | I16: الموبايل محتاج فورمات | J16: Claude draft | K16: Claude
A17: L016 | B17: لوج إن | C17: لوجين|اعمل لوج ان|لوج اوت | D17: log in / log out | E17: Arabized English verb | F17: LOGIN | G17: SCORE | H17: Caller | I17: اعمل لوج إن بالأكونت بتاعك وانا معاك | J17: Claude draft | K17: Claude
A18: L017 | B18: ساين إن | C18: ساين ان|ساين أب|ساين اب | D18: sign in / sign up | E18: Arabized English verb | F18: LOGIN | G18: SCORE | H18: Caller | I18: اعمل ساين إن تاني | J18: Claude draft | K18: Claude
A19: L018 | B19: سكان | C19: اعمل سكان|سكانها | D19: scan | E19: Arabized English verb | F19: SCAN | G19: SCORE | H19: Caller | I19: اعمل سكان للكيو آر كود ده | J19: Claude draft | K19: Claude | L19: QR scam
A20: L019 | B20: كوبي | C20: اعمل كوبي|كوبي بيست|بيست | D20: copy / paste | E20: Arabized English verb | F20: COPY | G20: SCORE | H20: Caller | I20: اعمل كوبي للكود وابعتهولي | J20: Claude draft | K20: Claude
A21: L020 | B21: سيند | C21: اعمل سيند|سيندها | D21: send | E21: Arabized English verb | F21: SEND | G21: SCORE | H21: Caller | I21: دوس سيند | J21: Claude draft | K21: Claude
A22: L021 | B22: ديليت | C22: امسح|اعمل ديليت|ديليتها | D22: delete | E22: Arabized English verb | F22: DELETE | G22: SCORE | H22: Caller | I22: اعمل ديليت للرسالة بعد ما تبعتها | J22: Claude draft | K22: Claude | L22: hiding traces
A23: L022 | B23: بلوك | C23: اعمل بلوك|اتبلك|اتبلوك|انبلوك | D23: block / unblock | E23: Arabized English verb | F23: BLOCK | G23: SCORE | H23: Caller | I23: الكارت هيتعمله بلوك لو ماأكدتش | J23: Claude draft | K23: Claude
A24: L023 | B24: فعّل | C24: اكتيف|اعمل اكتيفيت|اتفعّل|تفعيل | D24: activate | E24: Arabized English verb | F24: ACTIVATE | G24: SCORE | H24: Caller | I24: محتاجين نفعّل الخدمة دلوقتي | J24: Claude draft | K24: Claude
A25: L024 | B25: فيرفاي | C25: فريفاي|اعمل فيرفاي|فيرفيكيشن | D25: verify | E25: Arabized English verb | F25: VERIFY | G25: SCORE | H25: Caller | I25: محتاج أعمل فيرفاي للأكونت | J25: Claude draft | K25: Claude
A26: L025 | B26: هاك | C26: اتهكر|اتهاك|هكر|هاكر | D26: hack / hacked | E26: Arabized English verb | F26: HACKED | G26: SCORE | H26: Caller | I26: حسابك اتهكر ولازم نأمنه | J26: Claude draft | K26: Claude | L26: fear pretext
A27: L026 | B27: فريز | C27: اتعمله فريز|تجميد|اتجمّد | D27: freeze | E27: Arabized English verb | F27: FREEZE | G27: SCORE | H27: Caller | I27: الحساب هيتعمله فريز النهارده | J27: Claude draft | K27: Claude
A28: L027 | B28: سبسكرايب | C28: اشترك|اتشترك|سبسكرايب | D28: subscribe | E28: Arabized English verb | F28: SUBSCRIBE | G28: NEUTRAL | H28: Both | I28: انت مشترك في خدمة جديدة | J28: Claude draft | K28: Claude
A29: L028 | B29: ريفاند | C29: استرداد|رجّع الفلوس|ريفند | D29: refund | E29: Arabized English verb | F29: REFUND | G29: SCORE | H29: Caller | I29: هنعملك ريفاند بس محتاجين بيانات الكارت | J29: Claude draft | K29: Claude | L29: refund pretext
A30: L029 | B30: شارج | C30: اشحن|شحن|اشحنلي | D30: charge / top up | E30: Arabized English verb | F30: TOP_UP | G30: SCORE | H30: Caller | I30: اشحنلي كارت بمية جنيه | J30: Claude draft | K30: Claude
A31: L030 | B31: رن | C31: رنّلي|ارن|رنة|اديني رنة | D31: ring (missed call) | E31: Arabized English verb | F31: CALL | G31: NEUTRAL | H31: Both | I31: اديني رنة على الرقم ده | J31: Claude draft | K31: Claude
A32: L031 | B32: كول | C32: اعمل كول|فويس كول|فيديو كول | D32: call | E32: Arabized English verb | F32: CALL | G32: NEUTRAL | H32: Both | I32: هعملك كول تاني بعد شوية | J32: Claude draft | K32: Claude
A33: L032 | B33: ريبلاي | C33: رد|اعمل ريبلاي | D33: reply | E33: Arabized English verb | F33: REPLY | G33: NEUTRAL | H33: Both | I33: اعمل ريبلاي على الرسالة بكلمة نعم | J33: Claude draft | K33: Claude
A34: L033 | B34: كليك | C34: اضغط|دوس|اعمل كليك | D34: click | E34: Arabized English verb | F34: CLICK | G34: SCORE | H34: Caller | I34: دوس على اللينك اللي جالك | J34: Claude draft | K34: Claude
A35: L034 | B35: سيت أب | C35: اعمل سيت اب|سيتاب | D35: set up | E35: Arabized English verb | F35: SETUP | G35: NEUTRAL | H35: Both | I35: هعملك سيت أب للأبلكيشن | J35: Claude draft | K35: Claude
A36: L035 | B36: فولو أب | C36: فولو اب|هتابع|متابعة | D36: follow up | E36: Arabized English verb | F36: FOLLOW_UP | G36: NEUTRAL | H36: Both | I36: هعمل فولو أب مع حضرتك بكرة | J36: Claude draft | K36: Claude
A37: L036 | B37: بوك | C37: احجز|اعمل بوكينج|بوكينج | D37: book | E37: Arabized English verb | F37: BOOK | G37: NEUTRAL | H37: Both | I37: احجزلك ميعاد في الفرع | J37: Claude draft | K37: Claude
A38: L037 | B38: لينك | C38: اللينك|لينكات|رابط | D38: link | E38: English loanword / tech term | F38: LINK | G38: HARD | H38: Caller | I38: هبعتلك لينك افتحه ودخل بياناتك | J38: Claude draft | K38: Claude | L38: link + enter data = phishing
A39: L038 | B39: أبلكيشن | C39: ابلكيشن|ابليكيشن|الابلكيشن|التطبيق|أبلكيشن | D39: application (app) | E39: English loanword / tech term | F39: APP | G39: SCORE | H39: Both | I39: نزّل الأبلكيشن ده من اللينك | J39: Claude draft | K39: Claude
A40: L039 | B40: الأكونت | C40: اكونت|اكاونت|الاكاونت|حساب | D40: account | E40: English loanword / tech term | F40: ACCOUNT | G40: SCORE | H40: Both | I40: الأكونت بتاعك عليه مشكلة | J40: Claude draft | K40: Claude
A41: L040 | B41: يوزر | C41: يوزر نيم|اليوزر|اسم المستخدم | D41: username | E41: English loanword / tech term | F41: USERNAME | G41: HARD | H41: Caller | I41: قولّي اليوزر بتاعك | J41: Claude draft | K41: Claude
A42: L041 | B42: إيميل | C42: ايميل|الايميل|جيميل|البريد | D42: email | E42: English loanword / tech term | F42: EMAIL | G42: SCORE | H42: Both | I42: ابعتلي الإيميل اللي مسجّل بيه | J42: Claude draft | K42: Claude
A43: L042 | B43: نوتيفيكيشن | C43: نوتيفكيشن|اشعار|إشعار | D43: notification | E43: English loanword / tech term | F43: NOTIFICATION | G43: SCORE | H43: Caller | I43: هيجيلك نوتيفيكيشن دوس موافق | J43: Claude draft | K43: Claude
A44: L043 | B44: مسدج | C44: ميسج|مسج|رسالة|اس ام اس|SMS | D44: message / SMS | E44: English loanword / tech term | F44: SMS | G44: SCORE | H44: Both | I44: جالك مسدج دلوقتي؟ | J44: Claude draft | K44: Claude
A45: L044 | B45: سكرين | C45: سكرين شوت|اسكرين|سكرينة|صوّر الشاشة | D45: screenshot | E45: English loanword / tech term | F45: SCREENSHOT | G45: HARD | H45: Caller | I45: ابعتهولي سكرين | J45: Claude draft | K45: Claude | L45: screenshot of OTP/card = sharing it
A46: L045 | B46: الشاشة | C46: شاشتك|شير الشاشة | D46: screen | E46: English loanword / tech term | F46: SCREEN | G46: SCORE | H46: Caller | I46: افتحلي الشاشة عشان أشوف | J46: Claude draft | K46: Claude
A47: L046 | B47: سيستم | C47: السيستم|النظام | D47: system | E47: English loanword / tech term | F47: SYSTEM | G47: CONTEXT | H47: Both | I47: السيستم واقع عندنا | J47: Claude draft | K47: Claude | L47: classic excuse
A48: L047 | B48: سيرفر | C48: السيرفر | D48: server | E48: English loanword / tech term | F48: SYSTEM | G48: CONTEXT | H48: Both | I48: فيه مشكلة في السيرفر | J48: Claude draft | K48: Claude
A49: L048 | B49: داتا | C49: الداتا|بيانات|البيانات | D49: data | E49: English loanword / tech term | F49: DATA | G49: SCORE | H49: Both | I49: محتاجين نحدث الداتا بتاعتك | J49: Claude draft | K49: Claude
A50: L049 | B50: كيو آر | C50: كيو ار كود|QR|باركود | D50: QR code | E50: English loanword / tech term | F50: QR | G50: SCORE | H50: Caller | I50: امسح الكيو آر كود ده | J50: Claude draft | K50: Claude
A51: L050 | B51: أوفر | C51: عرض|العرض|اوفر | D51: offer | E51: English loanword / tech term | F51: OFFER | G51: SCORE | H51: Caller | I51: عندنا أوفر لحضرتك لفترة محدودة | J51: Claude draft | K51: Claude
A52: L051 | B52: بونص | C52: بونس|مكافأة | D52: bonus | E52: English loanword / tech term | F52: PRIZE | G52: SCORE | H52: Caller | I52: كسبت بونص على الخط | J52: Claude draft | K52: Claude
A53: L052 | B53: كاش باك | C53: كاشباك|كاش باك | D53: cashback | E53: English loanword / tech term | F53: PRIZE | G53: SCORE | H53: Caller | I53: ليك كاش باك محتاج تستلمه | J53: Claude draft | K53: Claude
A54: L053 | B54: برومو كود | C54: بروموكود|كود خصم|كوبون | D54: promo code | E54: English loanword / tech term | F54: PRIZE | G54: SCORE | H54: Caller | I54: هبعتلك برومو كود | J54: Claude draft | K54: Claude | L54: promo-code pretext for OTP
A55: L054 | B55: جيفت كارد | C55: جفت كارد|كارت هدية | D55: gift card | E55: English loanword / tech term | F55: GIFT_CARD | G55: SCORE | H55: Caller | I55: اشتريلي جيفت كارد وابعتلي الكود | J55: Claude draft | K55: Claude
A56: L055 | B56: أوردر | C56: اوردر|الطلب|طلبية | D56: order | E56: English loanword / tech term | F56: ORDER | G56: CONTEXT | H56: Both | I56: الأوردر بتاعك واقف في الجمارك | J56: Claude draft | K56: Claude | L56: delivery scam
A57: L056 | B57: ديليفري | C57: الدليفري|المندوب|شحنة | D57: delivery | E57: English loanword / tech term | F57: DELIVERY | G57: CONTEXT | H57: Both | I57: أنا الديليفري ومحتاج الكود عشان أسلّم | J57: Claude draft | K57: Claude
A58: L057 | B58: سابورت | C58: تك سابورت|الدعم الفني|الدعم | D58: support | E58: English loanword / tech term | F58: SUPPORT | G58: CONTEXT | H58: Caller | I58: أنا من التك سابورت | J58: Claude draft | K58: Claude
A59: L058 | B59: هيلب ديسك | C59: الهيلب ديسك|هيلبديسك | D59: help desk | E59: English loanword / tech term | F59: SUPPORT | G59: CONTEXT | H59: Caller | I59: معاك الهيلب ديسك | J59: Claude draft | K59: Claude
A60: L059 | B60: آي تي | C60: IT|الاي تي|اي تي | D60: IT department | E60: English loanword / tech term | F60: SUPPORT | G60: CONTEXT | H60: Caller | I60: أنا من الآي تي في الشركة | J60: Claude draft | K60: Claude
A61: L060 | B61: كول سنتر | C61: الكول سنتر|خدمة العملاء | D61: call centre | E61: English loanword / tech term | F61: SUPPORT | G61: CONTEXT | H61: Caller | I61: بكلمك من الكول سنتر | J61: Claude draft | K61: Claude
A62: L061 | B62: برانش | C62: الفرع|البرانش | D62: branch | E62: English loanword / tech term | F62: BRANCH | G62: CONTEXT | H62: Both | I62: مش محتاج تروح البرانش | J62: Claude draft | K62: Claude | L62: with 'مش محتاج' -> verification bypass
A63: L062 | B63: مانجر | C63: مانيجر|المدير|الماناجر | D63: manager | E63: English loanword / tech term | F63: AUTHORITY | G63: SCORE | H63: Caller | I63: المانجر طالب الموضوع ده حالاً | J63: Claude draft | K63: Claude
A64: L063 | B64: سيكيوريتي | C64: سكيوريتي|الأمن|أمن المعلومات | D64: security | E64: English loanword / tech term | F64: SECURITY | G64: CONTEXT | H64: Caller | I64: أنا من السيكيوريتي | J64: Claude draft | K64: Claude
A65: L064 | B65: ترانزاكشن | C65: ترانسكشن|عملية|المعاملة | D65: transaction | E65: English loanword / tech term | F65: TRANSACTION | G65: SCORE | H65: Caller | I65: فيه ترانزاكشن مشبوهة على كارتك | J65: Claude draft | K65: Claude
A66: L065 | B66: بالانس | C66: الرصيد|البالانس | D66: balance | E66: English loanword / tech term | F66: BALANCE | G66: SCORE | H66: Both | I66: البالانس بتاعك كام؟ | J66: Claude draft | K66: Claude
A67: L066 | B67: ليميت | C67: الحد|الليميت | D67: limit | E67: English loanword / tech term | F67: LIMIT | G67: SCORE | H67: Caller | I67: هنرفعلك الليميت | J67: Claude draft | K67: Claude
A68: L067 | B68: واتس | C68: واتساب|الواتس|الوتس | D68: WhatsApp | E68: English loanword / tech term | F68: WHATSAPP | G68: SCORE | H68: Caller | I68: ابعتلي على الواتس | J68: Claude draft | K68: Claude | L68: moving to WhatsApp
A69: L068 | B69: تليجرام | C69: التليجرام|تلجرام | D69: Telegram | E69: English loanword / tech term | F69: WHATSAPP | G69: SCORE | H69: Caller | I69: كلمني على تليجرام | J69: Claude draft | K69: Claude
A70: L069 | B70: إني ديسك | C70: انى ديسك|اني دسك|انيديسك|AnyDesk | D70: AnyDesk | E70: English loanword / tech term | F70: REMOTE_APP | G70: HARD | H70: Caller | I70: نزّل إني ديسك وقولّي الرقم اللي ظاهر | J70: Claude draft | K70: Claude
A71: L070 | B71: تيم فيوير | C71: تيم فيور|تيمفيوير|TeamViewer | D71: TeamViewer | E71: English loanword / tech term | F71: REMOTE_APP | G71: HARD | H71: Caller | I71: افتح تيم فيوير | J71: Claude draft | K71: Claude
A72: L071 | B72: زووم | C72: زوم|Zoom | D72: Zoom | E72: English loanword / tech term | F72: REMOTE_APP | G72: SCORE | H72: Caller | I72: ادخل على زووم وشير الشاشة | J72: Claude draft | K72: Claude
A73: L072 | B73: تديني | C73: اديني|ادّيني|تدّيني|ممكن تديني | D73: give me | E73: Request verb | F73: REQUEST | G73: HARD | H73: Caller | I73: ممكن تديني الcvv | J73: Claude draft | K73: Claude | L73: HARD only together with a secret object
A74: L073 | B74: ابعتلي | C74: ابعتهولي|ابعتهالي|ابعتلي|تبعتلي|هتبعتلي | D74: send me | E74: Request verb | F74: REQUEST | G74: HARD | H74: Caller | I74: ابعتلي الكود اللي جالك | J74: Claude draft | K74: Claude
A75: L074 | B75: قولّي | C75: قولي|قولهولي|تقولّي|قولهالي | D75: tell me | E75: Request verb | F75: REQUEST | G75: HARD | H75: Caller | I75: قولّي الرقم اللي في الرسالة | J75: Claude draft | K75: Claude
A76: L075 | B76: اقرالي | C76: اقراهولي|اقرأ|اقرا|تقرالي | D76: read (it) to me | E76: Request verb | F76: REQUEST | G76: HARD | H76: Caller | I76: اقرالي رقم الكارت كامل | J76: Claude draft | K76: Claude
A77: L076 | B77: هاتلي | C77: هاتهولي|جيبلي|هاته | D77: bring me / get me | E77: Request verb | F77: REQUEST | G77: HARD | H77: Caller | I77: هاتلي الكارت وقولّي اللي وراه | J77: Claude draft | K77: Claude
A78: L077 | B78: املّيني | C78: امليني|مليهولي|مليهوني|مليني | D78: dictate to me | E78: Request verb | F78: REQUEST | G78: HARD | H78: Caller | I78: املّيني الأرقام واحدة واحدة | J78: Claude draft | K78: Claude
A79: L078 | B79: اكتبلي | C79: اكتبهولي|اكتب | D79: write (it) for me | E79: Request verb | F79: REQUEST | G79: HARD | H79: Caller | I79: اكتبلي الكود في الشات | J79: Claude draft | K79: Claude
A80: L079 | B80: صوّرلي | C80: صوّرهولي|صوّر|اعملي صورة | D80: photograph it for me | E80: Request verb | F80: REQUEST | G80: HARD | H80: Caller | I80: صوّرلي الكارت من الوشين | J80: Claude draft | K80: Claude
A81: L080 | B81: حوّل | C81: حوّلي|حوّلهم|اعمل تحويل|نحوّل | D81: transfer | E81: Request verb | F81: PAYMENT | G81: HARD | H81: Caller | I81: حوّل الفلوس على الحساب ده | J81: Claude draft | K81: Claude
A82: L081 | B82: ادفع | C82: ادفعلي|سدّد|اعمل دفع | D82: pay | E82: Request verb | F82: PAYMENT | G82: HARD | H82: Caller | I82: ادفع الرسوم دلوقتي عشان الحساب مايتقفلش | J82: Claude draft | K82: Claude
A83: L082 | B83: دوس | C83: اضغط|دوسلي|اضغط على | D83: press / tap | E83: Request verb | F83: CLICK | G83: SCORE | H83: Caller | I83: دوس على الزرار الأخضر | J83: Claude draft | K83: Claude
A84: L083 | B84: افتح | C84: افتحلي|افتح اللينك|افتح الرسالة | D84: open | E84: Request verb | F84: CLICK | G84: SCORE | H84: Caller | I84: افتح الرسالة اللي لسه جايالك | J84: Claude draft | K84: Claude
A85: L084 | B85: ادخل | C85: ادخل على|خش على|اخش | D85: go into / enter | E85: Request verb | F85: CLICK | G85: SCORE | H85: Caller | I85: خش على الأبلكيشن وروح للإعدادات | J85: Claude draft | K85: Claude
... A95: L094 | B95: الcvv | C95: cvv|سي في في|السي في في|سيفيفي|التلات أرقام اللي ورا | D95: card security code | E95: Secret object | F95: CVV | G95: HARD | H95: Caller | I95: ممكن تديني الcvv | J95: Claude draft | K95: Claude
A96: L095 | B96: رقم الكارت | C96: رقم الكرت|رقم الفيزا|رقم كارت|الستاشر رقم | D96: card number | E96: Secret object | F96: CARD_NUMBER | G96: HARD | H96: Caller | I96: اقرالي رقم الكارت كامل | J96: Claude draft | K96: Claude | L96: الستاشر رقم = the 16 digits
A97: L096 | B97: تاريخ الانتهاء | C97: الاكسباير|اكسبايري|تاريخ انتهاء الكارت | D97: expiry date | E97: Secret object | F97: CARD_EXPIRY | G97: HARD | H97: Caller | I97: وتاريخ الانتهاء اللي على الكارت؟ | J97: Claude draft | K97: Claude
A98: L097 | B98: الرقم القومي | C98: رقم البطاقة|الرقم القومي بتاعك|البطاقة | D98: national ID number | E98: Secret object | F98: NATIONAL_ID | G98: SCORE | H98: Caller | I98: محتاج الرقم القومي للتأكيد | J98: Claude draft | K98: Claude | L98: often legitimately asked - score only
A99: L098 | B99: صورة البطاقة | C99: صورة البطاقة|البطاقة وش وضهر|صورة الباسبور | D99: photo of ID card | E99: Secret object | F99: NATIONAL_ID | G99: SCORE | H99: Caller | I99: ابعتلي صورة البطاقة وش وضهر | J99: Claude draft | K99: Claude
A100: L099 | B100: بيانات الكارت | C100: بيانات الفيزا|بيانات الكرت | D100: card details | E100: Secret object | F100: CARD_NUMBER | G100: HARD | H100: Caller | I100: أكّدلي بيانات الكارت | J100: Claude draft | K100: Claude
A101: L100 | B101: كود التحويل | C101: كود السحب|كود الاستلام | D101: transfer / withdrawal code | E101: Secret object | F101: OTP | G101: HARD | H101: Caller | I101: قولّي كود الاستلام | J101: Claude draft | K101: Claude
A102: L101 | B102: الرقم اللي ظاهر | C102: الرقم اللي ظاهرلك|الآي دي|الاي دي | D102: the ID shown (remote app) | E102: Secret object | F102: REMOTE_ID | G102: HARD | H102: Caller | I102: قولّي الرقم اللي ظاهر في البرنامج | J102: Claude draft | K102: Claude | L102: AnyDesk ID
A103: L102 | B103: فلوس | C103: الفلوس|فلوسك|مبلغ | D103: money | E103: Money & payment | F103: MONEY | G103: SCORE | H103: Both | I103: فلوسك في أمان معانا | J103: Claude draft | K103: Claude
A104: L103 | B104: الفيزا | C104: فيزا|الكارت|الكرت|كارت البنك|ماستر كارد | D104: bank card (any brand) | E104: Money & payment | F104: CARD | G104: SCORE | H104: Both | I104: الفيزا بتاعتك هتتوقف | J104: Claude draft | K104: Claude | L104: Egyptians say فيزا for any card
A105: L104 | B105: المحفظة | C105: محفظة|محفظتك|المحفظة الإلكترونية | D105: mobile wallet | E105: Money & payment | F105: WALLET | G105: SCORE | H105: Both | I105: حوّل على المحفظة | J105: Claude draft | K105: Claude
A106: L105 | B106: فودافون كاش | C106: فودافون|ڤودافون كاش|فودافون كيش | D106: Vodafone Cash wallet | E106: Money & payment | F106: WALLET | G106: SCORE | H106: Both | I106: ابعتهم فودافون كاش على الرقم ده | J106: Claude draft | K106: Claude
A107: L106 | B107: انستاباي | C107: انستا باي|إنستاباي|InstaPay | D107: InstaPay | E107: Money & payment | F107: WALLET | G107: SCORE | H107: Both | I107: حوّلهم انستاباي | J107: Claude draft | K107: Claude
A108: L107 | B108: أورانج كاش | C108: اورانج كاش|اتصالات كاش|وي باي | D108: Orange / e& / WE wallet | E108: Money & payment | F108: WALLET | G108: SCORE | H108: Both | I108: ابعت على أورانج كاش | J108: Claude draft | K108: Claude
A109: L108 | B109: فوري | C109: فورى|ماكينة فوري|كود فوري | D109: Fawry payments | E109: Money & payment | F109: PAYMENT | G109: SCORE | H109: Both | I109: ادفع بكود فوري | J109: Claude draft | K109: Claude
...

Sheet Summary
A1: Lexicon summary (live counts from the Lexicon tab)
A3: Category | B3: Words | C3: Verified
A4: Address term / rapport | B4: =COUNTIF(Lexicon!$E$2:$E$1000,A4) | C4: =COUNTIFS(Lexicon!$E$2:$E$1000,A4,Lexicon!$J$2:$J$1000,"Verified")
A5: Arabized English verb | B5: =COUNTIF(Lexicon!$E$2:$E$1000,A5) | C5: =COUNTIFS(Lexicon!$E$2:$E$1000,A5,Lexicon!$J$2:$J$1000,"Verified")
A6: Claimed identity / authority | B6: =COUNTIF(Lexicon!$E$2:$E$1000,A6) | C6: =COUNTIFS(Lexicon!$E$2:$E$1000,A6,Lexicon!$J$2:$J$1000,"Verified")
A7: English loanword / tech term | B7: =COUNTIF(Lexicon!$E$2:$E$1000,A7) | C7: =COUNTIFS(Lexicon!$E$2:$E$1000,A7,Lexicon!$J$2:$J$1000,"Verified")
A8: Everyday Egyptian | B8: =COUNTIF(Lexicon!$E$2:$E$1000,A8) | C8: =COUNTIFS(Lexicon!$E$2:$E$1000,A8,Lexicon!$J$2:$J$1000,"Verified")
A9: Money & payment | B9: =COUNTIF(Lexicon!$E$2:$E$1000,A9) | C9: =COUNTIFS(Lexicon!$E$2:$E$1000,A9,Lexicon!$J$2:$J$1000,"Verified")
A10: Pressure & secrecy | B10: =COUNTIF(Lexicon!$E$2:$E$1000,A10) | C10: =COUNTIFS(Lexicon!$E$2:$E$1000,A10,Lexicon!$J$2:$J$1000,"Verified")
A11: Request verb | B11: =COUNTIF(Lexicon!$E$2:$E$1000,A11) | C11: =COUNTIFS(Lexicon!$E$2:$E$1000,A11,Lexicon!$J$2:$J$1000,"Verified")
A12: Scam pretext / phrase | B12: =COUNTIF(Lexicon!$E$2:$E$1000,A12) | C12: =COUNTIFS(Lexicon!$E$2:$E$1000,A12,Lexicon!$J$2:$J$1000,"Verified")
A13: Secret object | B13: =COUNTIF(Lexicon!$E$2:$E$1000,A13) | C13: =COUNTIFS(Lexicon!$E$2:$E$1000,A13,Lexicon!$J$2:$J$1000,"Verified")
A14: Spoken numbers | B14: =COUNTIF(Lexicon!$E$2:$E$1000,A14) | C14: =COUNTIFS(Lexicon!$E$2:$E$1000,A14,Lexicon!$J$2:$J$1000,"Verified")
A15: Total | B15: =SUM(B4:B14) | C15: =SUM(C4:C14)
A17: Risk role | B17: Words
A18: HARD | B18: =COUNTIF(Lexicon!$G$2:$G$1000,A18)
A19: SCORE | B19: =COUNTIF(Lexicon!$G$2:$G$1000,A19)
A20: CONTEXT | B20: =COUNTIF(Lexicon!$G$2:$G$1000,A20)
A21: NEUTRAL | B21: =COUNTIF(Lexicon!$G$2:$G$1000,A21)
A23: Verified so far | B23: =IFERROR(C15/B15,0)

Sheet Transcription guide
A1: Transcription guideline (use the same rules for every recording)
A2: Rule | B2: Example
A3: Write Egyptian as spoken - never convert to formal Arabic | B3: عايز (not أريد)، دلوقتي (not الآن)
A4: English acronyms and brand names in Latin letters | B4: OTP, CVV, PIN, IT, AnyDesk, InstaPay
A5: ال attached to an English word: keep it attached, as spoken | B5: الcvv، الotp
A6: Arabized English verbs in Arabic letters, as pronounced | B6: اتشيك، هكنسلهالك، فورودهولي
A7: English nouns Egyptians use every day in Arabic letters | B7: الباسورد، اللينك، الأبلكيشن، الأكونت
A8: Digits spoken one by one: write each as a digit | B8: صفر واحد خمسة -> 0 1 5
A9: Keep Egyptian ج/ق as heard | B9: جالك (not قالك)
A10: Don't add punctuation you didn't hear; no diacritics
A11: Unclear word: write [?] - never guess | B11: ابعتلي [?] بسرعة
